{
  "trash_id": "7472a349ebd59119df8f74e4e03e5b4a",
  "trash_scores": {
    "default": 550
  },
  "name": "Anime Web Tier 01.5 (Custom Muxers)",
  "includeCustomFormatWhenRenaming": false,
  "specifications": [
    {
      "name": "WEBDL",
      "implementation": "SourceSpecification",
      "negate": false,
      "required": false,
      "fields": {
        "value": 7
      }
    },
    {
      "name": "WEBRIP",
      "implementation": "SourceSpecification",
      "negate": false,
      "required": false,
      "fields": {
        "value": 8
      }
    },
    {
      "name": "DemiHuman",
      "implementation": "ReleaseTitleSpecification",
      "negate": false,
      "required": false,
      "fields": {
        "value": "\\[DemiHuman\\]|-DemiHuman\\b"
      }
    },
    {
      "name": "GLORY",
      "implementation": "ReleaseTitleSpecification",
      "negate": false,
      "required": false,
      "fields": {
        "value": "\\[GLORY\\]|-GLORY\\b"
      }
    },
    {
      "name": "Heavenrend",
      "implementation": "ReleaseTitleSpecification",
      "negate": false,
      "required": false,
      "fields": {
        "value": "\\b(Heavenrend)\\b"
      }
    },
    {
      "name": "Nirvana",
      "implementation": "ReleaseTitleSpecification",
      "negate": false,
      "required": false,
      "fields": {
        "value": "\\[Nirvana\\]|-Nirvana\\b"
      }
    },
    {
      "name": "Starsugen",
      "implementation": "ReleaseTitleSpecification",
      "negate": false,
      "required": false,
      "fields": {
        "value": "\\b(Starsugen)\\b"
      }
    },
    {
      "name": "Zoombie",
      "implementation": "ReleaseTitleSpecification",
      "negate": false,
      "required": false,
      "fields": {
        "value": "\\b(Zoombie)\\b"
      }
    }
  ]
}
